agentic_kit_eda/__init__.py
agentic_kit_eda/bootstrap.py
agentic_kit_eda/graph/__init__.py
agentic_kit_eda/graph/schema.py
agentic_kit_eda/graph/tool_call_async_interrupt_graph.py
agentic_kit_eda/graph/tool_call_interrupt_graph.py
agentic_kit_eda/graph/tool_call_ws_interrupt_graph.py
agentic_kit_eda/infrastructure/__init__.py
agentic_kit_eda/infrastructure/celery/__init__.py
agentic_kit_eda/infrastructure/celery/celery_app.py
agentic_kit_eda/infrastructure/celery/schema.py
agentic_kit_eda/infrastructure/event_driven/__init__.py
agentic_kit_eda/infrastructure/event_driven/pub_sub/__init__.py
agentic_kit_eda/infrastructure/event_driven/pub_sub/redis_publish.py
agentic_kit_eda/infrastructure/event_driven/pub_sub/redis_pubsub_manager.py
agentic_kit_eda/infrastructure/event_driven/pub_sub/redis_subscriber.py
agentic_kit_eda/infrastructure/event_driven/ws/__init__.py
agentic_kit_eda/infrastructure/event_driven/ws/ws_message_handler_manager.py
agentic_kit_eda/infrastructure/queue/__init__.py
agentic_kit_eda/infrastructure/queue/inner_message_queue.py
agentic_kit_eda/infrastructure/queue/redis_hash.py
agentic_kit_eda/infrastructure/queue/redis_stack.py
agentic_kit_eda/infrastructure/queue/schema.py
agentic_kit_eda/infrastructure/redis/__init__.py
agentic_kit_eda/infrastructure/redis/schema.py
agentic_kit_eda/infrastructure/rpc/__init__.py
agentic_kit_eda/infrastructure/rpc/message.py
agentic_kit_eda/infrastructure/rpc/message_handler.py
agentic_kit_eda/infrastructure/rpc/session.py
agentic_kit_eda/infrastructure/rpc/session_mananger.py
agentic_kit_eda/infrastructure/rpc/fastapi/__init__.py
agentic_kit_eda/infrastructure/rpc/fastapi/ws_connection_manager.py
agentic_kit_eda/infrastructure/rpc/fastapi/ws_server.py
agentic_kit_eda/manager/__init__.py
agentic_kit_eda/manager/base.py
agentic_kit_eda/manager/flat_toolkit_manager.py
agentic_kit_eda/manager/ws_toolkit_manager.py
agentic_kit_eda/scheduler/__init__.py
agentic_kit_eda/scheduler/breakpoint_manager.py
agentic_kit_eda-0.0.5.dist-info/METADATA
agentic_kit_eda-0.0.5.dist-info/WHEEL
agentic_kit_eda-0.0.5.dist-info/top_level.txt
agentic_kit_eda-0.0.5.dist-info/RECORD
